pynaviz/__init__.py
pynaviz/base_plot.py
pynaviz/cli.py
pynaviz/controller.py
pynaviz/controller_group.py
pynaviz/events.py
pynaviz/interval_set.py
pynaviz/plot_manager.py
pynaviz/synchronization_rules.py
pynaviz/utils.py
pynaviz/audiovideo/__init__.py
pynaviz/audiovideo/audio_handling.py
pynaviz/audiovideo/base_audiovideo.py
pynaviz/audiovideo/skeleton_plot.py
pynaviz/audiovideo/video_handling.py
pynaviz/audiovideo/video_plot.py
pynaviz/audiovideo/video_worker.py
pynaviz/qt/__init__.py
pynaviz/qt/drop_down_dict_builder.py
pynaviz/qt/icons.py
pynaviz/qt/interval_sets_selection.py
pynaviz/qt/mainwindow.py
pynaviz/qt/tsdframe_selection.py
pynaviz/qt/widget_list_selection.py
pynaviz/qt/widget_menu.py
pynaviz/qt/widget_plot.py
pynaviz/qt/icons/favicon.ico
pynaviz/threads/data_streaming.py
pynaviz/threads/metadata_to_color_maps.py
pynaviz-0.1.2.dist-info/licenses/LICENSE
pynaviz-0.1.2.dist-info/METADATA
pynaviz-0.1.2.dist-info/WHEEL
pynaviz-0.1.2.dist-info/entry_points.txt
pynaviz-0.1.2.dist-info/top_level.txt
pynaviz-0.1.2.dist-info/RECORD
