Metadata-Version: 2.4
Name: pynaviz
Version: 0.1.2
Summary: Life made easier.
Author: pynaviz authors
License:                     GNU GENERAL PUBLIC LICENSE
Keywords: neuroscience,visualization,pynapple
Classifier: Intended Audience :: Science/Research
Classifier: Natural Language :: English
Classifier: Programming Language :: Python :: 3
Classifier: Programming Language :: Python :: 3.10
Requires-Python: >=3.9
License-File: LICENSE
Requires-Dist: pygfx>=0.15.3
Requires-Dist: pynapple>=0.9.0
Requires-Dist: glfw
Requires-Dist: matplotlib
Requires-Dist: numpy
Requires-Dist: av>=16.0.0
Provides-Extra: qt
Requires-Dist: pyside6; extra == "qt"
Provides-Extra: dev
Requires-Dist: pip-tools; extra == "dev"
Requires-Dist: pytest; extra == "dev"
Requires-Dist: pytest-qt; extra == "dev"
Requires-Dist: pytest-cov; extra == "dev"
Requires-Dist: matplotlib>=3.7; extra == "dev"
Requires-Dist: nox; extra == "dev"
Requires-Dist: ruff; extra == "dev"
Requires-Dist: isort; extra == "dev"
Requires-Dist: click; extra == "dev"
Requires-Dist: imageio; extra == "dev"
Requires-Dist: pyside6; extra == "dev"
Requires-Dist: fsspec; extra == "dev"
Requires-Dist: aiohttp; extra == "dev"
Requires-Dist: requests; extra == "dev"
Provides-Extra: docs
Requires-Dist: matplotlib; extra == "docs"
Requires-Dist: zarr; extra == "docs"
Requires-Dist: seaborn; extra == "docs"
Requires-Dist: tqdm; extra == "docs"
Requires-Dist: numpydoc; extra == "docs"
Requires-Dist: sphinx; extra == "docs"
Requires-Dist: pydata-sphinx-theme; extra == "docs"
Requires-Dist: sphinx-autodoc-typehints; extra == "docs"
Requires-Dist: sphinx-copybutton; extra == "docs"
Requires-Dist: sphinx-design; extra == "docs"
Requires-Dist: sphinx-issues; extra == "docs"
Requires-Dist: sphinxcontrib-apidoc; extra == "docs"
Requires-Dist: myst-parser; extra == "docs"
Requires-Dist: myst-nb; extra == "docs"
Requires-Dist: sphinx-autobuild; extra == "docs"
Requires-Dist: sphinx-contributors; extra == "docs"
Requires-Dist: pyside6; extra == "docs"
Requires-Dist: imageio; extra == "docs"
Dynamic: license-file
